sivtools/__init__.py
sivtools/data_structures/__init__.py
sivtools/data_structures/deque.py
sivtools/data_structures/linked_list.py
sivtools/data_structures/mapping.py
sivtools/data_structures/priority_queue.py
sivtools/data_structures/stack.py
sivtools/utilities/__init__.py
sivtools/utilities/deconstruct.py
sivtools/utilities/decorators.py
sivtools/utilities/logging.py
sivtools-0.1.0.dist-info/LICENSE
sivtools-0.1.0.dist-info/WHEEL
sivtools-0.1.0.dist-info/METADATA
sivtools-0.1.0.dist-info/RECORD
