Metadata-Version: 2.1
Name: sivtools
Version: 0.1.0
Summary: General purpose toolbox
Home-page: https://github.com/alysivji/sivtools
License: MIT
Keywords: toolbox utilities
Author: Aly Sivji
Author-email: alysivji@gmail.com
Requires-Python: >=3.3,<4
Classifier: Development Status :: 3 - Alpha
Classifier: License :: OSI Approved :: MIT License
Classifier: Programming Language :: Python :: 3.8
Classifier: Programming Language :: Python :: 3.7
Classifier: Programming Language :: Python :: 3.6
Classifier: Programming Language :: Python :: 3.5
Classifier: Programming Language :: Python :: 3.4
Classifier: Programming Language :: Python :: 3.3
Classifier: Programming Language :: Python :: Implementation :: PyPy
